pyappify/__init__.py
pyappify/main.py
pyappify-1.0.2.dist-info/METADATA
pyappify-1.0.2.dist-info/WHEEL
pyappify-1.0.2.dist-info/entry_points.txt
pyappify-1.0.2.dist-info/top_level.txt
pyappify-1.0.2.dist-info/RECORD
